<VideoStream timebaseNumerator="1" timebaseDenomenator="1000">
<Group pts="42" duration="984" size="3304" />
<Group pts="1043" duration="7995" size="984088" />
<Group pts="9176" duration="3280" size="1081177" />
<Group pts="12513" duration="1927" size="558741" />
<Group pts="14473" duration="1271" size="423188" />
<Group pts="15766" duration="1271" size="450988" />
<Group pts="17059" duration="3321" size="1212986" />
<Group pts="20437" duration="1722" size="505886" />
<Group pts="22189" duration="1804" size="540077" />
<Group pts="24024" duration="1763" size="318677" />
<Group pts="25817" duration="2542" size="515053" />
<Group pts="28403" duration="9389" size="1005228" />
<Group pts="37955" duration="2706" size="628164" />
<Group pts="40707" duration="2009" size="316879" />
<Group pts="42751" duration="3157" size="514301" />
<Group pts="45963" duration="1804" size="263260" />
<Group pts="47798" duration="4797" size="412102" />
<Group pts="52678" duration="2501" size="419710" />
<Group pts="55222" duration="5371" size="735027" />
<Group pts="60686" duration="1271" size="418587" />
<Group pts="61979" duration="1148" size="279738" />
<Group pts="63146" duration="2009" size="757591" />
<Group pts="65232" duration="1763" size="401610" />
<Group pts="66984" duration="4428" size="460233" />
<Group pts="71488" duration="4346" size="455399" />
<Group pts="75909" duration="5125" size="977313" />
<Group pts="81123" duration="3403" size="543734" />
<Group pts="84585" duration="6314" size="717106" />
<Group pts="91008" duration="6970" size="1274381" />
<Group pts="98098" duration="3649" size="167502" />
<Group pts="101810" duration="4182" size="299111" />
<Group pts="106064" duration="1189" size="196825" />
<Group pts="107357" duration="5863" size="523506" />
<Group pts="113238" duration="5248" size="1740688" />
<Group pts="118702" duration="4961" size="2025643" />
<Group pts="123624" duration="3608" size="3737204" />
<Group pts="127294" duration="3854" size="1798495" />
<Group pts="131256" duration="1066" size="201059" />
<Group pts="132299" duration="3403" size="804068" />
<Group pts="135761" duration="1353" size="675586" />
<Group pts="137137" duration="5043" size="991589" />
<Group pts="142267" duration="5330" size="2201741" />
<Group pts="147689" duration="1968" size="729200" />
<Group pts="149691" duration="6355" size="3727211" />
<Group pts="156156" duration="2624" size="1209751" />
<Group pts="158950" duration="1353" size="207224" />
<Group pts="160202" duration="2583" size="418320" />
<Group pts="162871" duration="6806" size="2664485" />
<Group pts="169753" duration="7298" size="4193689" />
<Group pts="177177" duration="1189" size="318701" />
<Group pts="178387" duration="1599" size="703265" />
<Group pts="180013" duration="5002" size="2219334" />
<Group pts="185102" duration="9922" size="2798105" />
<Group pts="195529" duration="5740" size="1127187" />
<Group pts="201034" duration="3198" size="255101" />
<Group pts="204287" duration="2132" size="172653" />
<Group pts="206456" duration="10086" size="778061" />
<Group pts="216883" duration="4838" size="282737" />
<Group pts="221638" duration="4387" size="247181" />
<Group pts="226101" duration="10250" size="424596" />
<Group pts="236528" duration="2378" size="161915" />
<Group pts="238947" duration="9963" size="643885" />
<Group pts="249374" duration="1435" size="103414" />
<Group pts="250542" duration="2829" size="238224" />
<Group pts="253420" duration="4879" size="282623" />
<Group pts="258383" duration="1968" size="414762" />
<Group pts="260510" duration="5822" size="579695" />
<Group pts="266308" duration="5330" size="477440" />
<Group pts="271730" duration="9307" size="795470" />
<Group pts="281198" duration="7872" size="686769" />
<Group pts="289206" duration="1476" size="438413" />
<Group pts="290707" duration="3075" size="652212" />
<Group pts="293835" duration="2460" size="402529" />
<Group pts="296338" duration="7380" size="446141" />
<Group pts="303845" duration="8159" size="399415" />
<Group pts="312145" duration="7954" size="447373" />
<Group pts="320237" duration="4510" size="295661" />
<Group pts="324825" duration="5289" size="349116" />
<Group pts="330205" duration="10045" size="770376" />
<Group pts="340632" duration="3034" size="274048" />
<Group pts="343510" duration="1968" size="117697" />
<Group pts="345512" duration="2460" size="137244" />
<Group pts="348014" duration="1968" size="222169" />
<Group pts="350016" duration="3813" size="1012214" />
<Group pts="353895" duration="10086" size="618070" />
<Group pts="364322" duration="3362" size="211341" />
<Group pts="367576" duration="9471" size="660797" />
<Group pts="377210" duration="5330" size="677226" />
<Group pts="382632" duration="3854" size="643195" />
<Group pts="386553" duration="4920" size="943993" />
<Group pts="391558" duration="5207" size="335652" />
<Group pts="396855" duration="1107" size="78063" />
<Group pts="397981" duration="1394" size="177819" />
<Group pts="399399" duration="1230" size="346108" />
<Group pts="400650" duration="2829" size="446616" />
<Group pts="403528" duration="3034" size="213126" />
<Group pts="406615" duration="6355" size="484646" />
<Group pts="413079" duration="10045" size="802595" />
<Group pts="423506" duration="3321" size="328702" />
<Group pts="426676" duration="8241" size="561809" />
<Group pts="435060" duration="3567" size="621604" />
<Group pts="438688" duration="6847" size="626180" />
<Group pts="445654" duration="4592" size="663001" />
<Group pts="450325" duration="2747" size="560224" />
<Group pts="453119" duration="1886" size="430542" />
<Group pts="455038" duration="1640" size="846581" />
<Group pts="456706" duration="1886" size="262373" />
<Group pts="458625" duration="7544" size="1441122" />
<Group pts="466299" duration="2542" size="157150" />
<Group pts="468885" duration="10004" size="945911" />
<Group pts="479312" duration="8118" size="1011338" />
<Group pts="487320" duration="4469" size="508290" />
<Group pts="491866" duration="3362" size="362075" />
<Group pts="495286" duration="4059" size="1408538" />
<Group pts="499416" duration="10045" size="854911" />
<Group pts="509843" duration="1968" size="325892" />
<Group pts="511636" duration="2091" size="368395" />
<Group pts="513763" duration="3895" size="364652" />
<Group pts="517726" duration="2952" size="982338" />
<Group pts="520729" duration="3567" size="569015" />
<Group pts="524357" duration="1353" size="177365" />
<Group pts="525734" duration="1312" size="328686" />
<Group pts="527068" duration="3157" size="489558" />
<Group pts="530280" duration="2050" size="296214" />
<Group pts="532365" duration="10004" size="1208542" />
<Group pts="542792" duration="5904" size="398384" />
<Group pts="548548" duration="7626" size="1247440" />
<Group pts="556306" duration="4100" size="403179" />
<Group pts="560477" duration="1968" size="162637" />
<Group pts="562479" duration="1312" size="189389" />
<Group pts="563813" duration="4346" size="397634" />
<Group pts="568234" duration="10004" size="1016593" />
<Group pts="578411" duration="1476" size="367158" />
<Group pts="579913" duration="1640" size="415377" />
<Group pts="581581" duration="2378" size="227332" />
<Group pts="584000" duration="6560" size="634802" />
<Group pts="590673" duration="5412" size="573191" />
<Group pts="596179" duration="7667" size="909041" />
<Group pts="603978" duration="3854" size="862364" />
<Group pts="607899" duration="3116" size="274963" />
<Group pts="611069" duration="3895" size="449975" />
<Group pts="615031" duration="4305" size="388201" />
<Group pts="619410" duration="5289" size="1230761" />
<Group pts="624791" duration="7544" size="519450" />
<Group pts="632465" duration="4510" size="964593" />
<Group pts="637053" duration="1476" size="123624" />
<Group pts="638555" duration="3485" size="199256" />
<Group pts="642100" duration="10004" size="879289" />
<Group pts="652527" duration="7216" size="1606458" />
<Group pts="659617" duration="6232" size="760281" />
<Group pts="665957" duration="5617" size="758229" />
<Group pts="671671" duration="9922" size="659971" />
<Group pts="682098" duration="4305" size="524093" />
<Group pts="686144" duration="2337" size="288584" />
<Group pts="688521" duration="5740" size="753345" />
<Group pts="694360" duration="6683" size="759768" />
<Group pts="701159" duration="6150" size="425481" />
<Group pts="707415" duration="2542" size="369366" />
<Group pts="710001" duration="4387" size="375898" />
<Group pts="714464" duration="5248" size="674814" />
<Group pts="719802" duration="3895" size="788088" />
<Group pts="723765" duration="3362" size="641496" />
<Group pts="727185" duration="2132" size="607815" />
<Group pts="729354" duration="2091" size="320885" />
<Group pts="731481" duration="1271" size="209555" />
<Group pts="732774" duration="1886" size="135166" />
<Group pts="734692" duration="1148" size="92737" />
<Group pts="735860" duration="1353" size="917184" />
<Group pts="737237" duration="2911" size="1275433" />
<Group pts="740198" duration="1763" size="430218" />
<Group pts="741991" duration="1107" size="735354" />
<Group pts="743117" duration="2665" size="1735709" />
<Group pts="745828" duration="6601" size="430394" />
<Group pts="752543" duration="2009" size="691898" />
<Group pts="754587" duration="1558" size="671309" />
<Group pts="756172" duration="2091" size="356626" />
<Group pts="758299" duration="1435" size="342925" />
<Group pts="759759" duration="1107" size="135935" />
<Group pts="760885" duration="2870" size="339082" />
<Group pts="763805" duration="1968" size="960113" />
<Group pts="765807" duration="4305" size="1018421" />
<Group pts="770186" duration="1517" size="435858" />
<Group pts="771729" duration="1394" size="224664" />
<Group pts="773147" duration="2624" size="902875" />
<Group pts="775817" duration="1804" size="1038960" />
<Group pts="777652" duration="3977" size="491581" />
<Group pts="781698" duration="3321" size="566082" />
<Group pts="785076" duration="2296" size="304676" />
<Group pts="787412" duration="4141" size="2119861" />
<Group pts="791624" duration="3280" size="869721" />
<Group pts="794961" duration="2337" size="226186" />
<Group pts="797338" duration="1312" size="650581" />
<Group pts="798673" duration="2337" size="1057444" />
<Group pts="801050" duration="2501" size="510362" />
<Group pts="803594" duration="4428" size="747123" />
<Group pts="808099" duration="3813" size="589285" />
<Group pts="811978" duration="2583" size="237861" />
<Group pts="814605" duration="4633" size="418395" />
<Group pts="819319" duration="2132" size="333808" />
<Group pts="821487" duration="2911" size="363711" />
<Group pts="824449" duration="6519" size="1434275" />
<Group pts="831080" duration="5330" size="539668" />
<Group pts="836502" duration="1107" size="130058" />
<Group pts="837628" duration="3321" size="323216" />
<Group pts="841007" duration="2460" size="217478" />
<Group pts="843509" duration="2132" size="279996" />
<Group pts="845678" duration="3608" size="686178" />
<Group pts="849349" duration="5617" size="1777082" />
<Group pts="855063" duration="2009" size="467983" />
<Group pts="857106" duration="1148" size="186236" />
<Group pts="858274" duration="4428" size="1028803" />
<Group pts="862779" duration="5904" size="909655" />
<Group pts="868785" duration="2583" size="367554" />
<Group pts="871412" duration="3321" size="179492" />
<Group pts="874791" duration="1845" size="748390" />
<Group pts="876667" duration="4059" size="893738" />
<Group pts="880797" duration="3444" size="823700" />
<Group pts="884300" duration="2788" size="208819" />
<Group pts="887136" duration="1271" size="397471" />
<Group pts="888429" duration="1148" size="703963" />
<Group pts="889597" duration="2214" size="923733" />
<Group pts="891849" duration="2132" size="332417" />
<Group pts="894018" duration="2378" size="552380" />
<Group pts="896437" duration="1394" size="419308" />
<Group pts="897855" duration="1886" size="617673" />
<Group pts="899774" duration="2870" size="675985" />
<Group pts="902693" duration="2132" size="352094" />
<Group pts="904862" duration="3526" size="190091" />
<Group pts="908449" duration="2911" size="813651" />
<Group pts="911411" duration="7790" size="2082479" />
<Group pts="919335" duration="4879" size="1231584" />
<Group pts="924298" duration="10250" size="1114382" />
<Group pts="934725" duration="5617" size="481500" />
<Group pts="940440" duration="2706" size="313025" />
<Group pts="943192" duration="2829" size="375891" />
<Group pts="946070" duration="5781" size="594049" />
<Group pts="951951" duration="2829" size="218658" />
<Group pts="954829" duration="2583" size="257803" />
<Group pts="957457" duration="4305" size="407349" />
<Group pts="961836" duration="5002" size="520710" />
<Group pts="966924" duration="3731" size="566088" />
<Group pts="970720" duration="9512" size="772482" />
<Group pts="980396" duration="9922" size="625421" />
<Group pts="990823" duration="8446" size="612473" />
<Group pts="999081" duration="1394" size="151540" />
<Group pts="1000500" duration="3895" size="660520" />
<Group pts="1004462" duration="5002" size="337614" />
<Group pts="1009550" duration="1353" size="239593" />
<Group pts="1010927" duration="6806" size="577123" />
<Group pts="1017850" duration="4510" size="700505" />
<Group pts="1022438" duration="4305" size="519106" />
<Group pts="1026817" duration="2829" size="488939" />
<Group pts="1029695" duration="3567" size="532474" />
<Group pts="1033324" duration="5371" size="549655" />
<Group pts="1038788" duration="7872" size="1434193" />
<Group pts="1046796" duration="9922" size="660413" />
<Group pts="1057223" duration="3731" size="253605" />
<Group pts="1060685" duration="5822" size="1313376" />
<Group pts="1066607" duration="5248" size="417903" />
<Group pts="1071946" duration="2419" size="407433" />
<Group pts="1074407" duration="5740" size="983485" />
<Group pts="1080246" duration="3649" size="188810" />
<Group pts="1083958" duration="5658" size="498783" />
<Group pts="1089714" duration="3321" size="197741" />
<Group pts="1093092" duration="1353" size="107643" />
<Group pts="1094468" duration="2829" size="596510" />
<Group pts="1097346" duration="9061" size="958764" />
<Group pts="1106564" duration="6560" size="808253" />
<Group pts="1113237" duration="5166" size="2157381" />
<Group pts="1118492" duration="5289" size="372124" />
<Group pts="1123873" duration="10004" size="809281" />
<Group pts="1134300" duration="7216" size="489247" />
<Group pts="1141390" duration="6642" size="624537" />
<Group pts="1148147" duration="3485" size="227108" />
<Group pts="1151692" duration="3649" size="231786" />
<Group pts="1155404" duration="4100" size="553463" />
<Group pts="1159700" duration="1189" size="200593" />
<Group pts="1160785" duration="2870" size="113242" />
<Group pts="1163704" duration="10209" size="2168456" />
<Group pts="1174131" duration="3116" size="778042" />
<Group pts="1177259" duration="4797" size="394577" />
<Group pts="1182139" duration="2419" size="147514" />
<Group pts="1184600" duration="4387" size="502849" />
<Group pts="1189063" duration="4633" size="519604" />
<Group pts="1193776" duration="1681" size="133579" />
<Group pts="1195486" duration="2255" size="440175" />
<Group pts="1197780" duration="10086" size="1383807" />
<Group pts="1208207" duration="2624" size="204948" />
<Group pts="1210710" duration="4264" size="1097432" />
<Group pts="1215047" duration="5781" size="497168" />
<Group pts="1220928" duration="4059" size="571962" />
<Group pts="1225057" duration="6847" size="381292" />
<Group pts="1232022" duration="984" size="439739" />
<Group pts="1233023" duration="7913" size="813870" />
<Group pts="1241073" duration="1353" size="209876" />
<Group pts="1242450" duration="2870" size="365399" />
<Group pts="1245369" duration="9963" size="1173278" />
<Group pts="1255796" duration="3608" size="327363" />
<Group pts="1259175" duration="2255" size="213512" />
<Group pts="1261469" duration="2378" size="544856" />
<Group pts="1263888" duration="5535" size="582055" />
<Group pts="1269518" duration="1640" size="250792" />
<Group pts="1271187" duration="9020" size="1694592" />
<Group pts="1280362" duration="7134" size="574124" />
<Group pts="1287745" duration="4223" size="477483" />
<Group pts="1291916" duration="7257" size="411038" />
<Group pts="1299298" duration="2624" size="300840" />
<Group pts="1301967" duration="2296" size="265046" />
<Group pts="1304303" duration="1435" size="87853" />
<Group pts="1305763" duration="7339" size="1011686" />
<Group pts="1313229" duration="2542" size="287079" />
<Group pts="1315815" duration="1312" size="77653" />
<Group pts="1317149" duration="2788" size="164350" />
<Group pts="1320110" duration="7749" size="1332591" />
<Group pts="1327868" duration="4797" size="510649" />
<Group pts="1332748" duration="4674" size="522527" />
<Group pts="1337503" duration="8610" size="1907924" />
<Group pts="1346262" duration="10209" size="1867285" />
<Group pts="1356647" duration="10127" size="2933342" />
<Group pts="1367074" duration="6642" size="1044576" />
<Group pts="1373706" duration="2173" size="149067" />
<Group pts="1375916" duration="8856" size="3070383" />
<Group pts="1384925" duration="8077" size="1859997" />
<Group pts="1393142" duration="2255" size="483886" />
<Group pts="1395477" duration="2829" size="272353" />
<Group pts="1398314" duration="7585" size="1786849" />
<Group pts="1406030" duration="7749" size="769855" />
<Group pts="1413913" duration="2091" size="240477" />
<Group pts="1416040" duration="1476" size="195463" />
<Group pts="1417541" duration="2009" size="298701" />
<Group pts="1419585" duration="1845" size="279894" />
<Group pts="1421462" duration="2460" size="383389" />
<Group pts="1423964" duration="2788" size="629942" />
<Group pts="1426800" duration="4182" size="345326" />
<Group pts="1431055" duration="1394" size="4542" />
</VideoStream>
