<VideoStream timebaseNumerator="1" timebaseDenomenator="1000">
<Group pts="0" duration="9922" size="2922353" />
<Group pts="10417" duration="3280" size="342988" />
<Group pts="13417" duration="5084" size="1362928" />
<Group pts="18583" duration="2378" size="27967" />
<Group pts="21000" duration="10168" size="904246" />
<Group pts="31417" duration="4510" size="193044" />
<Group pts="35917" duration="1763" size="391909" />
<Group pts="37708" duration="1599" size="434017" />
<Group pts="39333" duration="1394" size="503398" />
<Group pts="40750" duration="1107" size="473129" />
<Group pts="41875" duration="6232" size="3476376" />
<Group pts="48208" duration="6068" size="2278078" />
<Group pts="54375" duration="1025" size="316447" />
<Group pts="55417" duration="2214" size="369376" />
<Group pts="57667" duration="2665" size="2157300" />
<Group pts="60375" duration="5002" size="1158363" />
<Group pts="65458" duration="10168" size="2629061" />
<Group pts="75875" duration="6478" size="2931134" />
<Group pts="82375" duration="5207" size="3813901" />
<Group pts="87667" duration="10209" size="5509601" />
<Group pts="98083" duration="1189" size="222989" />
<Group pts="99250" duration="6273" size="4868646" />
<Group pts="105625" duration="10250" size="5011435" />
<Group pts="116042" duration="6437" size="3339068" />
<Group pts="122583" duration="1189" size="936177" />
<Group pts="123792" duration="1845" size="763610" />
<Group pts="125667" duration="1189" size="273353" />
<Group pts="126875" duration="5043" size="1436379" />
<Group pts="132000" duration="1804" size="46124" />
<Group pts="133958" duration="1353" size="19484" />
<Group pts="135375" duration="3403" size="1877035" />
<Group pts="138667" duration="1722" size="425105" />
<Group pts="140417" duration="1558" size="949111" />
<Group pts="142000" duration="1517" size="565734" />
<Group pts="143542" duration="5494" size="1688218" />
<Group pts="149125" duration="1722" size="919441" />
<Group pts="150875" duration="10250" size="1420404" />
<Group pts="161292" duration="2132" size="635941" />
<Group pts="163458" duration="1353" size="444756" />
<Group pts="164833" duration="8077" size="2478309" />
<Group pts="173042" duration="2788" size="453208" />
<Group pts="175875" duration="4059" size="2494794" />
<Group pts="180000" duration="4551" size="2506404" />
<Group pts="184625" duration="3608" size="1211218" />
<Group pts="188292" duration="1353" size="647259" />
<Group pts="189667" duration="2911" size="1108123" />
<Group pts="192625" duration="2829" size="1928813" />
<Group pts="195500" duration="2091" size="542089" />
<Group pts="197625" duration="2706" size="200402" />
<Group pts="200375" duration="1927" size="233896" />
<Group pts="202333" duration="3936" size="1367644" />
<Group pts="206333" duration="9512" size="1081982" />
<Group pts="216000" duration="4387" size="330652" />
<Group pts="220458" duration="3198" size="277956" />
<Group pts="223708" duration="2255" size="572790" />
<Group pts="226000" duration="2009" size="365053" />
<Group pts="228042" duration="2214" size="303881" />
<Group pts="230292" duration="4469" size="391700" />
<Group pts="234833" duration="5576" size="978125" />
<Group pts="240500" duration="3731" size="140753" />
<Group pts="244292" duration="2788" size="188321" />
<Group pts="247125" duration="2255" size="194054" />
<Group pts="249417" duration="1640" size="186959" />
<Group pts="251083" duration="1968" size="204563" />
<Group pts="253083" duration="2050" size="167091" />
<Group pts="255167" duration="2337" size="178970" />
<Group pts="257542" duration="3116" size="250016" />
<Group pts="260708" duration="2788" size="121823" />
<Group pts="263542" duration="4141" size="210447" />
<Group pts="267750" duration="9102" size="349066" />
<Group pts="277000" duration="3157" size="173279" />
<Group pts="280208" duration="2747" size="113586" />
<Group pts="283000" duration="2050" size="238418" />
<Group pts="285167" duration="2214" size="467533" />
<Group pts="287333" duration="2911" size="310653" />
<Group pts="290292" duration="2214" size="265346" />
<Group pts="292542" duration="3977" size="918250" />
<Group pts="296583" duration="2255" size="339341" />
<Group pts="298875" duration="1845" size="195652" />
<Group pts="300750" duration="1763" size="254883" />
<Group pts="302542" duration="2993" size="385179" />
<Group pts="305583" duration="7995" size="963252" />
<Group pts="313708" duration="3649" size="560204" />
<Group pts="317417" duration="5043" size="592326" />
<Group pts="322542" duration="1968" size="213477" />
<Group pts="324542" duration="4264" size="506576" />
<Group pts="328875" duration="1640" size="165369" />
<Group pts="330542" duration="3731" size="244428" />
<Group pts="334333" duration="1435" size="222040" />
<Group pts="335792" duration="2583" size="328487" />
<Group pts="338417" duration="1681" size="161600" />
<Group pts="340125" duration="3690" size="1195354" />
<Group pts="343875" duration="2337" size="499774" />
<Group pts="346250" duration="2911" size="166168" />
<Group pts="349292" duration="4387" size="262044" />
<Group pts="353667" duration="7421" size="1501372" />
<Group pts="361208" duration="1066" size="255857" />
<Group pts="362292" duration="1804" size="445691" />
<Group pts="364125" duration="2419" size="879408" />
<Group pts="366583" duration="1312" size="1071749" />
<Group pts="367917" duration="1107" size="713177" />
<Group pts="369042" duration="3280" size="1174999" />
<Group pts="372375" duration="2296" size="1157987" />
<Group pts="374708" duration="4592" size="1726494" />
<Group pts="379375" duration="5945" size="1525960" />
<Group pts="385417" duration="6109" size="1208538" />
<Group pts="391625" duration="2214" size="1021648" />
<Group pts="393875" duration="4182" size="1122738" />
<Group pts="398125" duration="1927" size="693434" />
<Group pts="400083" duration="902" size="507387" />
<Group pts="401208" duration="5412" size="1374503" />
<Group pts="406500" duration="2296" size="401940" />
<Group pts="408833" duration="2419" size="900426" />
<Group pts="411292" duration="4510" size="2631720" />
<Group pts="415875" duration="5945" size="1247177" />
<Group pts="421917" duration="1558" size="1597464" />
<Group pts="423500" duration="2993" size="2136203" />
<Group pts="426542" duration="2091" size="1242024" />
<Group pts="428667" duration="1599" size="447876" />
<Group pts="430292" duration="2747" size="518132" />
<Group pts="433083" duration="1189" size="710668" />
<Group pts="434292" duration="1927" size="971795" />
<Group pts="436250" duration="2296" size="1436010" />
<Group pts="438583" duration="3116" size="1617959" />
<Group pts="441750" duration="2378" size="1370150" />
<Group pts="444167" duration="1353" size="886843" />
<Group pts="445542" duration="2009" size="1502522" />
<Group pts="447583" duration="1230" size="662813" />
<Group pts="448833" duration="5863" size="957721" />
<Group pts="454792" duration="2829" size="666748" />
<Group pts="457875" duration="2337" size="214112" />
<Group pts="460042" duration="4551" size="926491" />
<Group pts="464667" duration="10045" size="1732272" />
<Group pts="475083" duration="3239" size="717239" />
<Group pts="478167" duration="10045" size="2240932" />
<Group pts="488583" duration="5289" size="1214996" />
<Group pts="493750" duration="4264" size="738595" />
<Group pts="498083" duration="1640" size="145675" />
<Group pts="499750" duration="2009" size="466658" />
<Group pts="501792" duration="3895" size="688021" />
<Group pts="505750" duration="10045" size="2233761" />
<Group pts="516167" duration="7872" size="1024259" />
<Group pts="523958" duration="10086" size="2055758" />
<Group pts="534208" duration="5453" size="646790" />
<Group pts="539750" duration="7216" size="549260" />
<Group pts="547083" duration="7462" size="1467268" />
<Group pts="554667" duration="5781" size="391447" />
<Group pts="560542" duration="2870" size="670306" />
<Group pts="563458" duration="1845" size="353066" />
<Group pts="565417" duration="3034" size="429335" />
<Group pts="568417" duration="4141" size="771822" />
<Group pts="572625" duration="2009" size="374932" />
<Group pts="574667" duration="2091" size="487400" />
<Group pts="576792" duration="1271" size="187752" />
<Group pts="578083" duration="8774" size="1503266" />
<Group pts="587000" duration="7872" size="1361700" />
<Group pts="595000" duration="2091" size="241622" />
<Group pts="597125" duration="1558" size="315241" />
<Group pts="598792" duration="1271" size="251640" />
<Group pts="600000" duration="4305" size="508938" />
<Group pts="604375" duration="3772" size="409256" />
<Group pts="608208" duration="4797" size="619028" />
<Group pts="613083" duration="9963" size="397165" />
<Group pts="623500" duration="2665" size="131252" />
<Group pts="625917" duration="5207" size="500823" />
<Group pts="631208" duration="10045" size="910749" />
<Group pts="641625" duration="2624" size="201048" />
<Group pts="644083" duration="4715" size="286904" />
<Group pts="648875" duration="5166" size="501866" />
<Group pts="654125" duration="4428" size="456277" />
<Group pts="658625" duration="3649" size="271129" />
<Group pts="662333" duration="2214" size="352314" />
<Group pts="664583" duration="4756" size="828335" />
<Group pts="669458" duration="3567" size="366811" />
<Group pts="673042" duration="10086" size="1824532" />
<Group pts="683458" duration="2706" size="500836" />
<Group pts="686042" duration="3526" size="940552" />
<Group pts="689625" duration="1722" size="294430" />
<Group pts="691375" duration="2952" size="244449" />
<Group pts="694375" duration="2009" size="228017" />
<Group pts="696417" duration="4797" size="251693" />
<Group pts="701292" duration="9758" size="297594" />
<Group pts="711208" duration="3854" size="531037" />
<Group pts="715125" duration="2460" size="366106" />
<Group pts="717625" duration="3690" size="928843" />
<Group pts="721375" duration="4100" size="361182" />
<Group pts="725542" duration="8733" size="1706062" />
<Group pts="734417" duration="2747" size="368064" />
<Group pts="737208" duration="1148" size="155365" />
<Group pts="738375" duration="2419" size="189767" />
<Group pts="740833" duration="3362" size="295870" />
<Group pts="744250" duration="2952" size="249900" />
<Group pts="747250" duration="3075" size="404607" />
<Group pts="750375" duration="2542" size="869234" />
<Group pts="752958" duration="8733" size="1036598" />
<Group pts="761833" duration="7134" size="523152" />
<Group pts="769083" duration="10168" size="2428643" />
<Group pts="779500" duration="3690" size="933902" />
<Group pts="783167" duration="1968" size="531852" />
<Group pts="785167" duration="1353" size="320201" />
<Group pts="786542" duration="1968" size="489835" />
<Group pts="788542" duration="4674" size="413831" />
<Group pts="793292" duration="5576" size="1054071" />
<Group pts="798958" duration="3567" size="977377" />
<Group pts="802583" duration="3731" size="1871620" />
<Group pts="806375" duration="1107" size="876151" />
<Group pts="807500" duration="1968" size="1281889" />
<Group pts="809500" duration="5699" size="4925715" />
<Group pts="815292" duration="1476" size="1080522" />
<Group pts="816792" duration="1476" size="452876" />
<Group pts="818292" duration="1148" size="1794857" />
<Group pts="819458" duration="1681" size="1040130" />
<Group pts="821167" duration="2706" size="1984141" />
<Group pts="823917" duration="1886" size="2104698" />
<Group pts="825833" duration="1107" size="735542" />
<Group pts="826958" duration="984" size="565146" />
<Group pts="827958" duration="2706" size="1435435" />
<Group pts="830708" duration="3936" size="605822" />
<Group pts="834708" duration="2378" size="1694127" />
<Group pts="837125" duration="2378" size="820096" />
<Group pts="839542" duration="1066" size="255419" />
<Group pts="840625" duration="984" size="148466" />
<Group pts="841625" duration="2747" size="896771" />
<Group pts="844417" duration="1763" size="802675" />
<Group pts="846208" duration="2542" size="1278203" />
<Group pts="848792" duration="1517" size="746703" />
<Group pts="850333" duration="1845" size="1606886" />
<Group pts="852208" duration="1722" size="853763" />
<Group pts="853958" duration="1148" size="898252" />
<Group pts="855125" duration="1107" size="1444983" />
<Group pts="856250" duration="1107" size="1362179" />
<Group pts="857375" duration="1763" size="1568355" />
<Group pts="859167" duration="5617" size="6136901" />
<Group pts="864875" duration="1476" size="1433685" />
<Group pts="866375" duration="1968" size="1443472" />
<Group pts="868375" duration="1189" size="674568" />
<Group pts="869583" duration="1558" size="836462" />
<Group pts="871167" duration="2009" size="2175685" />
<Group pts="873208" duration="1927" size="1299090" />
<Group pts="875167" duration="1189" size="669942" />
<Group pts="876375" duration="5084" size="1624502" />
<Group pts="881542" duration="2624" size="186766" />
<Group pts="884208" duration="1066" size="227102" />
<Group pts="885292" duration="3567" size="1037912" />
<Group pts="888917" duration="1927" size="929806" />
<Group pts="890875" duration="2337" size="1102922" />
<Group pts="893250" duration="1394" size="484043" />
<Group pts="894667" duration="8856" size="842171" />
<Group pts="903667" duration="2460" size="653851" />
<Group pts="906167" duration="2706" size="1412347" />
<Group pts="908917" duration="5904" size="723595" />
<Group pts="914917" duration="1312" size="629686" />
<Group pts="916250" duration="9840" size="8160022" />
<Group pts="926250" duration="2419" size="1022073" />
<Group pts="928708" duration="2132" size="931224" />
<Group pts="930875" duration="2296" size="1067386" />
<Group pts="933208" duration="2050" size="353329" />
<Group pts="935292" duration="3895" size="1180092" />
<Group pts="939250" duration="1558" size="266448" />
<Group pts="940833" duration="2091" size="212046" />
<Group pts="942958" duration="1804" size="168599" />
<Group pts="944792" duration="4510" size="336610" />
<Group pts="949375" duration="1353" size="582610" />
<Group pts="950750" duration="1558" size="702595" />
<Group pts="952333" duration="1804" size="172044" />
<Group pts="954167" duration="7626" size="726825" />
<Group pts="961917" duration="3321" size="1311399" />
<Group pts="965292" duration="1558" size="252526" />
<Group pts="966875" duration="3075" size="355530" />
<Group pts="970000" duration="2132" size="234297" />
<Group pts="972167" duration="4387" size="946451" />
<Group pts="976625" duration="6683" size="654100" />
<Group pts="983417" duration="2665" size="420578" />
<Group pts="986125" duration="4469" size="529439" />
<Group pts="990667" duration="6355" size="442708" />
<Group pts="997125" duration="2132" size="357473" />
<Group pts="999292" duration="10045" size="743135" />
<Group pts="1009708" duration="3731" size="210776" />
<Group pts="1013292" duration="5207" size="516026" />
<Group pts="1018583" duration="6109" size="758169" />
<Group pts="1024792" duration="6888" size="1052955" />
<Group pts="1031792" duration="1066" size="153555" />
<Group pts="1032875" duration="3567" size="350375" />
<Group pts="1036500" duration="1517" size="120091" />
<Group pts="1038042" duration="2337" size="179256" />
<Group pts="1040417" duration="2624" size="272089" />
<Group pts="1043083" duration="5084" size="301535" />
<Group pts="1048250" duration="2460" size="155774" />
<Group pts="1050750" duration="5330" size="246095" />
<Group pts="1056167" duration="3198" size="190182" />
<Group pts="1059417" duration="9717" size="296344" />
<Group pts="1069292" duration="5412" size="184491" />
<Group pts="1074792" duration="1148" size="252976" />
<Group pts="1075958" duration="4879" size="206609" />
<Group pts="1080917" duration="3895" size="296425" />
<Group pts="1084875" duration="6683" size="418394" />
<Group pts="1091667" duration="1107" size="146643" />
<Group pts="1092792" duration="5699" size="376235" />
<Group pts="1098583" duration="7790" size="1632948" />
<Group pts="1106500" duration="5330" size="3455704" />
<Group pts="1111917" duration="1353" size="801958" />
<Group pts="1113292" duration="1230" size="1121499" />
<Group pts="1114542" duration="2542" size="2220914" />
<Group pts="1117125" duration="10250" size="7790763" />
<Group pts="1127542" duration="5125" size="4946839" />
<Group pts="1132750" duration="10004" size="8593472" />
<Group pts="1142917" duration="6232" size="7797430" />
<Group pts="1149250" duration="10127" size="14041838" />
<Group pts="1159667" duration="10250" size="11315568" />
<Group pts="1169958" duration="5207" size="3533114" />
<Group pts="1175250" duration="10045" size="4394751" />
<Group pts="1185458" duration="5658" size="3599040" />
<Group pts="1191208" duration="984" size="1108557" />
<Group pts="1192250" duration="3690" size="622576" />
<Group pts="1196042" duration="1927" size="380968" />
<Group pts="1197917" duration="656" size="48026" />
</VideoStream>
