<VideoStream timebaseNumerator="1" timebaseDenomenator="1000">
<Group pts="0" duration="1107" size="24927" />
<Group pts="1418" duration="3567" size="231255" />
<Group pts="4755" duration="10127" size="3089343" />
<Group pts="15182" duration="5166" size="1904107" />
<Group pts="20312" duration="5207" size="1287452" />
<Group pts="25609" duration="4756" size="2059206" />
<Group pts="30447" duration="3403" size="343196" />
<Group pts="33992" duration="1271" size="127110" />
<Group pts="35202" duration="5043" size="2304274" />
<Group pts="40332" duration="4428" size="1268737" />
<Group pts="44836" duration="1230" size="138758" />
<Group pts="46088" duration="1476" size="282583" />
<Group pts="47589" duration="5535" size="706776" />
<Group pts="53220" duration="10045" size="8394086" />
<Group pts="63438" duration="10086" size="9571894" />
<Group pts="73699" duration="2173" size="682909" />
<Group pts="75909" duration="2419" size="1018616" />
<Group pts="78370" duration="3444" size="1275503" />
<Group pts="81873" duration="2091" size="700892" />
<Group pts="84001" duration="1599" size="639404" />
<Group pts="85627" duration="1025" size="540210" />
<Group pts="86670" duration="1394" size="456977" />
<Group pts="88088" duration="1886" size="652326" />
<Group pts="90007" duration="9348" size="1332322" />
<Group pts="99516" duration="2378" size="212668" />
<Group pts="101935" duration="1886" size="236232" />
<Group pts="103854" duration="2460" size="89867" />
<Group pts="106356" duration="7134" size="347578" />
<Group pts="113614" duration="1968" size="208225" />
<Group pts="115616" duration="4018" size="134857" />
<Group pts="119703" duration="2870" size="327131" />
<Group pts="122623" duration="3075" size="449996" />
<Group pts="125751" duration="943" size="143522" />
<Group pts="126710" duration="4059" size="147033" />
<Group pts="130839" duration="4346" size="201645" />
<Group pts="135260" duration="3321" size="243182" />
<Group pts="138639" duration="2255" size="139710" />
<Group pts="140932" duration="8938" size="290529" />
<Group pts="150025" duration="1722" size="128174" />
<Group pts="151777" duration="2911" size="141377" />
<Group pts="154738" duration="9922" size="332880" />
<Group pts="165165" duration="1763" size="126951" />
<Group pts="166625" duration="4100" size="95818" />
<Group pts="170796" duration="1927" size="92567" />
<Group pts="172756" duration="2829" size="169972" />
<Group pts="175634" duration="6191" size="177502" />
<Group pts="181932" duration="1968" size="92892" />
<Group pts="183934" duration="3813" size="62795" />
<Group pts="187813" duration="1558" size="182317" />
<Group pts="189398" duration="8528" size="150267" />
<Group pts="198073" duration="3321" size="133537" />
<Group pts="201451" duration="1353" size="164777" />
<Group pts="202828" duration="4346" size="218324" />
<Group pts="207249" duration="2050" size="227630" />
<Group pts="209334" duration="2583" size="241651" />
<Group pts="211962" duration="3690" size="366244" />
<Group pts="215716" duration="5166" size="222503" />
<Group pts="220971" duration="2255" size="136945" />
<Group pts="223265" duration="4018" size="167545" />
<Group pts="227352" duration="1476" size="373142" />
<Group pts="228854" duration="4797" size="160293" />
<Group pts="233734" duration="6273" size="144820" />
<Group pts="240115" duration="10004" size="386155" />
<Group pts="250542" duration="2255" size="79421" />
<Group pts="252586" duration="1722" size="90527" />
<Group pts="254337" duration="7134" size="304980" />
<Group pts="261595" duration="2624" size="116970" />
<Group pts="264264" duration="1025" size="177051" />
<Group pts="265307" duration="984" size="270027" />
<Group pts="266308" duration="1722" size="62696" />
<Group pts="268059" duration="5412" size="67130" />
<Group pts="273565" duration="2542" size="163757" />
<Group pts="276151" duration="1845" size="49382" />
<Group pts="278028" duration="10045" size="1300518" />
<Group pts="288455" duration="1312" size="139199" />
<Group pts="289581" duration="10045" size="376096" />
<Group pts="300008" duration="1312" size="82212" />
<Group pts="301134" duration="2460" size="93907" />
<Group pts="303637" duration="3649" size="238510" />
<Group pts="307349" duration="2952" size="227234" />
<Group pts="310352" duration="3280" size="281686" />
<Group pts="313688" duration="3731" size="121197" />
<Group pts="317484" duration="3280" size="147767" />
<Group pts="320821" duration="3649" size="572960" />
<Group pts="324574" duration="4223" size="184791" />
<Group pts="328829" duration="1599" size="210218" />
<Group pts="330455" duration="2788" size="303815" />
<Group pts="333291" duration="8651" size="649213" />
<Group pts="342092" duration="3239" size="253224" />
<Group pts="345720" duration="4305" size="215702" />
<Group pts="349766" duration="5986" size="327583" />
<Group pts="355856" duration="6109" size="213465" />
<Group pts="362070" duration="2091" size="59793" />
<Group pts="364197" duration="6027" size="315478" />
<Group pts="370328" duration="7626" size="600369" />
<Group pts="378086" duration="6191" size="165565" />
<Group pts="384384" duration="6601" size="959181" />
<Group pts="391099" duration="3198" size="266022" />
<Group pts="394352" duration="3936" size="140216" />
<Group pts="398356" duration="4182" size="297770" />
<Group pts="402611" duration="5412" size="199048" />
<Group pts="408116" duration="1476" size="89263" />
<Group pts="409618" duration="6150" size="477407" />
<Group pts="415874" duration="6191" size="478150" />
<Group pts="422172" duration="1476" size="182452" />
<Group pts="423673" duration="2419" size="55989" />
<Group pts="426134" duration="6601" size="147719" />
<Group pts="432849" duration="2214" size="150436" />
<Group pts="435101" duration="10045" size="468901" />
<Group pts="445528" duration="3034" size="245476" />
<Group pts="448406" duration="9963" size="332245" />
<Group pts="458833" duration="1353" size="41037" />
<Group pts="459918" duration="3444" size="234662" />
<Group pts="463421" duration="2173" size="73259" />
<Group pts="465632" duration="2296" size="97984" />
<Group pts="467968" duration="4633" size="253516" />
<Group pts="472681" duration="3116" size="191332" />
<Group pts="475850" duration="2788" size="173831" />
<Group pts="478687" duration="3936" size="164277" />
<Group pts="482691" duration="1681" size="50793" />
<Group pts="484401" duration="2091" size="39199" />
<Group pts="486528" duration="1845" size="530490" />
<Group pts="488488" duration="2993" size="891541" />
<Group pts="491491" duration="1394" size="329525" />
<Group pts="492867" duration="8979" size="758212" />
<Group pts="502002" duration="6601" size="132559" />
<Group pts="508717" duration="2050" size="199518" />
<Group pts="510802" duration="6765" size="154243" />
<Group pts="517684" duration="5617" size="196758" />
<Group pts="523398" duration="3690" size="93731" />
<Group pts="527152" duration="7585" size="613501" />
<Group pts="534868" duration="3321" size="129831" />
<Group pts="538246" duration="2911" size="194935" />
<Group pts="541207" duration="2460" size="147094" />
<Group pts="543710" duration="5248" size="407335" />
<Group pts="549049" duration="2419" size="215402" />
<Group pts="551509" duration="4879" size="137560" />
<Group pts="556473" duration="6109" size="488642" />
<Group pts="562687" duration="8364" size="309509" />
<Group pts="571196" duration="3444" size="125501" />
<Group pts="574699" duration="1148" size="191066" />
<Group pts="575867" duration="4428" size="433105" />
<Group pts="580371" duration="2173" size="359998" />
<Group pts="582582" duration="3239" size="410535" />
<Group pts="585877" duration="4428" size="745756" />
<Group pts="590381" duration="4510" size="167789" />
<Group pts="594969" duration="2952" size="633596" />
<Group pts="597972" duration="3608" size="1027923" />
<Group pts="601643" duration="6232" size="209799" />
<Group pts="607982" duration="10045" size="197946" />
<Group pts="618409" duration="2583" size="179783" />
<Group pts="620829" duration="6970" size="664885" />
<Group pts="627919" duration="1435" size="78863" />
<Group pts="629379" duration="5412" size="158991" />
<Group pts="634884" duration="7298" size="284572" />
<Group pts="642308" duration="4428" size="356331" />
<Group pts="646813" duration="1968" size="268181" />
<Group pts="648815" duration="3895" size="206816" />
<Group pts="652777" duration="9512" size="384010" />
<Group pts="662453" duration="5617" size="539551" />
<Group pts="668168" duration="2706" size="125052" />
<Group pts="670920" duration="1968" size="303711" />
<Group pts="672922" duration="6068" size="481752" />
<Group pts="679095" duration="1845" size="152372" />
<Group pts="680972" duration="9061" size="432397" />
<Group pts="690190" duration="9184" size="529985" />
<Group pts="699532" duration="8364" size="384967" />
<Group pts="708041" duration="5412" size="237445" />
<Group pts="713546" duration="3936" size="474380" />
<Group pts="717550" duration="2583" size="266272" />
<Group pts="720178" duration="4428" size="498822" />
<Group pts="724682" duration="4592" size="539762" />
<Group pts="729354" duration="2460" size="286796" />
<Group pts="731856" duration="7626" size="1012287" />
<Group pts="739614" duration="1230" size="225840" />
<Group pts="740865" duration="3485" size="561764" />
<Group pts="744410" duration="1476" size="633935" />
<Group pts="745912" duration="3116" size="714970" />
<Group pts="749082" duration="943" size="153225" />
<Group pts="750083" duration="10168" size="1560318" />
<Group pts="760510" duration="1517" size="306679" />
<Group pts="761928" duration="3075" size="361585" />
<Group pts="765056" duration="5371" size="449133" />
<Group pts="770520" duration="1804" size="231533" />
<Group pts="772355" duration="1312" size="142979" />
<Group pts="773690" duration="5002" size="989736" />
<Group pts="778778" duration="3198" size="203440" />
<Group pts="782031" duration="7380" size="457204" />
<Group pts="789539" duration="2911" size="306280" />
<Group pts="792500" duration="6765" size="1446266" />
<Group pts="799382" duration="2460" size="275626" />
<Group pts="801884" duration="8364" size="1728256" />
<Group pts="810393" duration="9061" size="1062495" />
<Group pts="819610" duration="6642" size="1027198" />
<Group pts="826367" duration="2788" size="256390" />
<Group pts="829203" duration="3034" size="339495" />
<Group pts="832290" duration="1927" size="531259" />
<Group pts="834250" duration="5166" size="375698" />
<Group pts="839505" duration="3239" size="645641" />
<Group pts="842800" duration="3157" size="275397" />
<Group pts="846012" duration="1763" size="314203" />
<Group pts="847847" duration="4879" size="425094" />
<Group pts="852769" duration="2460" size="145378" />
<Group pts="855271" duration="10004" size="708404" />
<Group pts="865698" duration="2870" size="183778" />
<Group pts="868368" duration="5658" size="488602" />
<Group pts="874123" duration="9963" size="470894" />
<Group pts="884550" duration="4551" size="312315" />
<Group pts="888888" duration="6847" size="1004510" />
<Group pts="895853" duration="3936" size="475893" />
<Group pts="899857" duration="3116" size="127205" />
<Group pts="903027" duration="3034" size="385339" />
<Group pts="906114" duration="5330" size="300853" />
<Group pts="911536" duration="4305" size="316113" />
<Group pts="915915" duration="3854" size="343880" />
<Group pts="919836" duration="2378" size="125631" />
<Group pts="922255" duration="9676" size="1287421" />
<Group pts="932098" duration="3280" size="251784" />
<Group pts="935435" duration="4059" size="406712" />
<Group pts="939564" duration="10209" size="2365820" />
<Group pts="949991" duration="10291" size="4046826" />
<Group pts="960418" duration="9881" size="4268389" />
<Group pts="970470" duration="3690" size="370189" />
<Group pts="974223" duration="4182" size="320753" />
<Group pts="978561" duration="1230" size="200564" />
<Group pts="979729" duration="2050" size="948714" />
<Group pts="982106" duration="6109" size="581240" />
<Group pts="988112" duration="2829" size="302770" />
<Group pts="990907" duration="4387" size="282031" />
<Group pts="995369" duration="984" size="147636" />
<Group pts="996370" duration="8364" size="339416" />
<Group pts="1004879" duration="4469" size="178727" />
<Group pts="1009425" duration="5125" size="354975" />
<Group pts="1014639" duration="9143" size="233747" />
<Group pts="1023940" duration="2460" size="120748" />
<Group pts="1026442" duration="9307" size="274431" />
<Group pts="1035910" duration="6314" size="537056" />
<Group pts="1042333" duration="9922" size="210819" />
<Group pts="1052760" duration="1845" size="140560" />
<Group pts="1054303" duration="1476" size="48515" />
<Group pts="1055805" duration="943" size="96336" />
<Group pts="1056764" duration="4592" size="228726" />
<Group pts="1061435" duration="1968" size="112647" />
<Group pts="1063437" duration="10086" size="334125" />
<Group pts="1073698" duration="3198" size="297195" />
<Group pts="1076951" duration="3936" size="301196" />
<Group pts="1080955" duration="1968" size="585576" />
<Group pts="1082957" duration="1722" size="616787" />
<Group pts="1084709" duration="1968" size="463347" />
<Group pts="1086711" duration="4305" size="619023" />
<Group pts="1091090" duration="4469" size="313481" />
<Group pts="1095636" duration="5453" size="176005" />
<Group pts="1101183" duration="4756" size="403203" />
<Group pts="1106022" duration="2378" size="227570" />
<Group pts="1108441" duration="3977" size="79190" />
<Group pts="1112486" duration="7872" size="1092876" />
<Group pts="1120494" duration="1968" size="81962" />
<Group pts="1122496" duration="7954" size="2483810" />
<Group pts="1130588" duration="7995" size="196092" />
<Group pts="1138763" duration="4018" size="92371" />
<Group pts="1142808" duration="1230" size="69314" />
<Group pts="1144060" duration="1476" size="174985" />
<Group pts="1145561" duration="1681" size="205212" />
<Group pts="1147271" duration="5412" size="610472" />
<Group pts="1152777" duration="4387" size="424299" />
<Group pts="1157239" duration="3936" size="80402" />
<Group pts="1161243" duration="1476" size="379511" />
<Group pts="1162745" duration="6437" size="119292" />
<Group pts="1169293" duration="3854" size="640785" />
<Group pts="1173214" duration="8774" size="123201" />
<Group pts="1182139" duration="7257" size="661425" />
<Group pts="1189605" duration="1435" size="177975" />
<Group pts="1190981" duration="5904" size="773399" />
<Group pts="1196987" duration="6888" size="591736" />
<Group pts="1203994" duration="1476" size="226782" />
<Group pts="1205496" duration="5289" size="389652" />
<Group pts="1210876" duration="1312" size="1060088" />
<Group pts="1212211" duration="1927" size="1126007" />
<Group pts="1214171" duration="3526" size="1237899" />
<Group pts="1217758" duration="5658" size="1610627" />
<Group pts="1223514" duration="3690" size="946953" />
<Group pts="1227268" duration="2952" size="1091049" />
<Group pts="1230271" duration="2460" size="571651" />
<Group pts="1232773" duration="2952" size="766206" />
<Group pts="1235776" duration="1476" size="136695" />
<Group pts="1237278" duration="7872" size="924478" />
<Group pts="1245286" duration="1722" size="326193" />
<Group pts="1247037" duration="3936" size="450643" />
<Group pts="1251041" duration="1681" size="276866" />
<Group pts="1252752" duration="3895" size="216471" />
<Group pts="1256714" duration="4059" size="326391" />
<Group pts="1260843" duration="4141" size="186851" />
<Group pts="1265055" duration="1230" size="31347" />
<Group pts="1266515" duration="10414" size="2007961" />
<Group pts="1276942" duration="10209" size="3331301" />
<Group pts="1287369" duration="10250" size="3284354" />
<Group pts="1297797" duration="10250" size="3667413" />
<Group pts="1308224" duration="10209" size="3965554" />
<Group pts="1318651" duration="10250" size="7161130" />
<Group pts="1329078" duration="10373" size="7816943" />
<Group pts="1339505" duration="10168" size="7897286" />
<Group pts="1349932" duration="5125" size="1545053" />
<Group pts="1355062" duration="1353" size="327422" />
<Group pts="1356438" duration="1107" size="175520" />
<Group pts="1357565" duration="3157" size="488784" />
<Group pts="1360776" duration="1763" size="467290" />
<Group pts="1362570" duration="1107" size="130210" />
<Group pts="1363696" duration="984" size="277862" />
<Group pts="1364697" duration="1312" size="778366" />
<Group pts="1366031" duration="3977" size="444193" />
</VideoStream>
